dpt_runtime/__init__.py
dpt_runtime/binary.py
dpt_runtime/charset.py
dpt_runtime/environment.py
dpt_runtime/environment_dict.py
dpt_runtime/input_filter.py
dpt_runtime/iterator.py
dpt_runtime/not_implemented_class.py
dpt_runtime/settings.py
dpt_runtime/stacked_dict.py
dpt_runtime/supports_mixin.py
dpt_runtime/exceptions/__init__.py
dpt_runtime/exceptions/io_exception.py
dpt_runtime/exceptions/not_implemented_exception.py
dpt_runtime/exceptions/operation_not_supported_exception.py
dpt_runtime/exceptions/traced_exception.py
dpt_runtime/exceptions/traced_exception_mixin.py
dpt_runtime/exceptions/type_exception.py
dpt_runtime/exceptions/value_exception.py
dpt_runtime/io/__init__.py
dpt_runtime/io/byte_buffer.py
dpt_runtime/io/descriptor_selector.py
dpt_runtime/io/file_like_copy_mixin.py
dpt_runtime/io/socket_reader.py
dpt_runtime-2.1.4.data/data/docs/LICENSE
dpt_runtime-2.1.4.data/data/docs/README
dpt_runtime-2.1.4.dist-info/LICENSE
dpt_runtime-2.1.4.dist-info/METADATA
dpt_runtime-2.1.4.dist-info/WHEEL
dpt_runtime-2.1.4.dist-info/top_level.txt
dpt_runtime-2.1.4.dist-info/RECORD
