Metadata-Version: 2.1
Name: dpt-runtime
Version: 2.1.4
Summary: Utility classes compatible with multiple Python runtime variants
Home-page: https://www.direct-netware.de/redirect?dpt;runtime
Author: direct Netware Group et al.
Author-email: web@direct-netware.de
License: MPL2
Platform: any
Classifier: Intended Audience :: Developers
Classifier: License :: OSI Approved :: Mozilla Public License 2.0 (MPL 2.0)
Classifier: Operating System :: OS Independent
Classifier: Programming Language :: Python
Classifier: Topic :: Software Development :: Libraries :: Python Modules
Requires-Dist: dpt-file (<2,>=1)
Requires-Dist: dpt-json (<2,>=1)
